README.rst
setup.py
ppas/__init__.py
ppas/ppas.py
ppas.egg-info/PKG-INFO
ppas.egg-info/SOURCES.txt
ppas.egg-info/dependency_links.txt
ppas.egg-info/entry_points.txt
ppas.egg-info/requires.txt
ppas.egg-info/top_level.txt