Metadata-Version: 1.1
Name: ppas
Version: 0.1.0
Summary: PostProcess Answer Sets
Home-page: https://github.com/vukk/ppas
Author: Unto Kuuranne
Author-email: unto.kuuranne@aalto.fi
License: UNKNOWN
Download-URL: https://github.com/vukk/ppas/tarball/v0.1.0
Keywords: asp,answer set programming,postprocess,clingo
Platform: UNKNOWN
Classifier: Programming Language :: Python
Classifier: Programming Language :: Python :: 3
Classifier: Intended Audience :: Science/Research
Classifier: Development Status :: 3 - Alpha
Classifier: License :: OSI Approved :: MIT License
